translator_project/__init__.py
translator_project/translator_lib.py
translator_project-3.0.2.dist-info/METADATA
translator_project-3.0.2.dist-info/WHEEL
translator_project-3.0.2.dist-info/RECORD
